<annotation>
	<folder>images</folder>
	<filename>003_472.jpg</filename>
	<path>/Users/ding/workspace/小车备份/dell_traffic2021/data/traffic/images/003_472.jpg</path>
	<source>
		<database>Unknown</database>
	</source>
	<size>
		<width>640</width>
		<height>480</height>
		<depth>3</depth>
	</size>
	<segmented>0</segmented>
	<object>
		<name>Stop</name>
		<pose>Unspecified</pose>
		<truncated>0</truncated>
		<difficult>0</difficult>
		<bndbox>
			<xmin>225</xmin>
			<ymin>133</ymin>
			<xmax>238</xmax>
			<ymax>147</ymax>
		</bndbox>
	</object>
	<object>
		<name>turn</name>
		<pose>Unspecified</pose>
		<truncated>0</truncated>
		<difficult>0</difficult>
		<bndbox>
			<xmin>247</xmin>
			<ymin>121</ymin>
			<xmax>302</xmax>
			<ymax>181</ymax>
		</bndbox>
	</object>
	<object>
		<name>turn</name>
		<pose>Unspecified</pose>
		<truncated>0</truncated>
		<difficult>0</difficult>
		<bndbox>
			<xmin>325</xmin>
			<ymin>140</ymin>
			<xmax>335</xmax>
			<ymax>153</ymax>
		</bndbox>
	</object>
	<object>
		<name>Check</name>
		<pose>Unspecified</pose>
		<truncated>0</truncated>
		<difficult>0</difficult>
		<bndbox>
			<xmin>448</xmin>
			<ymin>157</ymin>
			<xmax>465</xmax>
			<ymax>174</ymax>
		</bndbox>
	</object>
	<object>
		<name>crossing</name>
		<pose>Unspecified</pose>
		<truncated>0</truncated>
		<difficult>0</difficult>
		<bndbox>
			<xmin>532</xmin>
			<ymin>172</ymin>
			<xmax>562</xmax>
			<ymax>205</ymax>
		</bndbox>
	</object>
</annotation>
